MinecraftServerOpener/__init__.py
MinecraftServerOpener/error/__init__.py
MinecraftServerOpener/error/error.py
MinecraftServerOpener/menu/__init__.py
MinecraftServerOpener/menu/main.py
Miencraft_Server_Opener-0.1.dist-info/LICENSE.txt
Miencraft_Server_Opener-0.1.dist-info/METADATA
Miencraft_Server_Opener-0.1.dist-info/WHEEL
Miencraft_Server_Opener-0.1.dist-info/top_level.txt
Miencraft_Server_Opener-0.1.dist-info/RECORD
